{
  "experiment_config": {
    "n_cycles": 20000,
    "initial_drives": 0,
    "initial_actions": 6
  },
  "drive_space": {
    "total_drives": 5,
    "emerged_drives": 5,
    "drive_details": {
      "survival": {
        "weight": 1.0,
        "stability": 0.8299178646522216,
        "emerged": true,
        "activity_count": 50
      },
      "curiosity": {
        "weight": 1.0,
        "stability": 0.8299178646522216,
        "emerged": true,
        "activity_count": 50
      },
      "influence": {
        "weight": 1.0,
        "stability": 0.8299178646522216,
        "emerged": true,
        "activity_count": 50
      },
      "drive_emerged_at_cycle_1012": {
        "weight": 1.0,
        "stability": 0.8299178646522216,
        "emerged": true,
        "activity_count": 50
      },
      "drive_emerged_at_cycle_1017": {
        "weight": 1.0,
        "stability": 0.8299178646522216,
        "emerged": true,
        "activity_count": 50
      }
    }
  },
  "action_distribution": {
    "explore": 0.12635,
    "conserve": 0.1889,
    "socialize": 0.153,
    "learn": 0.1552,
    "rest": 0.25105,
    "create": 0.1255
  },
  "emerged_drive_list": [
    {
      "name": "survival",
      "weight": 1.0,
      "stability": 0.8299178646522216,
      "activity": 0.5214074193536519,
      "emerged": true,
      "emergence_cycle": null
    },
    {
      "name": "curiosity",
      "weight": 1.0,
      "stability": 0.8299178646522216,
      "activity": 0.5214074193536519,
      "emerged": true,
      "emergence_cycle": null
    },
    {
      "name": "influence",
      "weight": 1.0,
      "stability": 0.8299178646522216,
      "activity": 0.5214074193536519,
      "emerged": true,
      "emergence_cycle": null
    },
    {
      "name": "drive_emerged_at_cycle_1012",
      "weight": 1.0,
      "stability": 0.8299178646522216,
      "activity": 0.5214074193536519,
      "emerged": true,
      "emergence_cycle": null
    },
    {
      "name": "drive_emerged_at_cycle_1017",
      "weight": 1.0,
      "stability": 0.8299178646522216,
      "activity": 0.5214074193536519,
      "emerged": true,
      "emergence_cycle": null
    }
  ],
  "timestamp": "2026-04-03T20:04:26.280296",
  "framework": "OEF v1.0"
}