{
  "exp_id": 3,
  "seed": 456,
  "total_actions": 10000,
  "knowledge_acquired": 2955,
  "cumulative_reward": 694.2268493697595,
  "final_weights": {
    "survival": 0.18487572114671277,
    "curiosity": 0.5209942308262981,
    "influence": 0.20169218745363263,
    "optimization": 0.09243786057335639
  },
  "weight_history": [
    {
      "step": 100,
      "weights": {
        "survival": 0.20173173591784735,
        "curiosity": 0.38614611265722115,
        "influence": 0.31125628346600775,
        "optimization": 0.10086586795892367
      }
    },
    {
      "step": 200,
      "weights": {
        "survival": 0.20148479664909805,
        "curiosity": 0.38812162680721574,
        "influence": 0.30965117821913724,
        "optimization": 0.10074239832454902
      }
    },
    {
      "step": 300,
      "weights": {
        "survival": 0.20148586928609372,
        "curiosity": 0.38811304571125044,
        "influence": 0.309658150359609,
        "optimization": 0.10074293464304686
      }
    },
    {
      "step": 400,
      "weights": {
        "survival": 0.19990687503410567,
        "curiosity": 0.40074499972715494,
        "influence": 0.2993946877216866,
        "optimization": 0.09995343751705284
      }
    },
    {
      "step": 500,
      "weights": {
        "survival": 0.2010683504869409,
        "curiosity": 0.391453196104473,
        "influence": 0.30694427816511566,
        "optimization": 0.10053417524347046
      }
    },
    {
      "step": 600,
      "weights": {
        "survival": 0.20045513247690325,
        "curiosity": 0.39635894018477447,
        "influence": 0.30295836109987073,
        "optimization": 0.10022756623845162
      }
    },
    {
      "step": 700,
      "weights": {
        "survival": 0.19983234248953619,
        "curiosity": 0.40134126008371074,
        "influence": 0.29891022618198493,
        "optimization": 0.09991617124476809
      }
    },
    {
      "step": 800,
      "weights": {
        "survival": 0.200945627106896,
        "curiosity": 0.3924349831448322,
        "influence": 0.30614657619482377,
        "optimization": 0.100472813553448
      }
    },
    {
      "step": 900,
      "weights": {
        "survival": 0.19976549228083454,
        "curiosity": 0.401876061753324,
        "influence": 0.2984756998254242,
        "optimization": 0.09988274614041727
      }
    },
    {
      "step": 1000,
      "weights": {
        "survival": 0.2016478629190916,
        "curiosity": 0.3868170966472676,
        "influence": 0.31071110897409504,
        "optimization": 0.1008239314595458
      }
    },
    {
      "step": 1100,
      "weights": {
        "survival": 0.1998984201116232,
        "curiosity": 0.4008126391070145,
        "influence": 0.29933973072555065,
        "optimization": 0.0999492100558116
      }
    },
    {
      "step": 1200,
      "weights": {
        "survival": 0.20033388483652959,
        "curiosity": 0.3973289213077636,
        "influence": 0.30217025143744203,
        "optimization": 0.10016694241826479
      }
    },
    {
      "step": 1300,
      "weights": {
        "survival": 0.19911702847877735,
        "curiosity": 0.4070637721697815,
        "influence": 0.29426068511205244,
        "optimization": 0.09955851423938868
      }
    },
    {
      "step": 1400,
      "weights": {
        "survival": 0.1972272786680141,
        "curiosity": 0.4221817706558876,
        "influence": 0.28197731134209125,
        "optimization": 0.09861363933400705
      }
    },
    {
      "step": 1500,
      "weights": {
        "survival": 0.19768776056237447,
        "curiosity": 0.41849791550100457,
        "influence": 0.2849704436554337,
        "optimization": 0.09884388028118724
      }
    },
    {
      "step": 1600,
      "weights": {
        "survival": 0.19674737143559845,
        "curiosity": 0.42602102851521284,
        "influence": 0.27885791433138957,
        "optimization": 0.09837368571779923
      }
    },
    {
      "step": 1700,
      "weights": {
        "survival": 0.1962127442907743,
        "curiosity": 0.43029804567380625,
        "influence": 0.27538283789003243,
        "optimization": 0.09810637214538714
      }
    },
    {
      "step": 1800,
      "weights": {
        "survival": 0.19652728824330437,
        "curiosity": 0.42778169405356553,
        "influence": 0.277427373581478,
        "optimization": 0.09826364412165219
      }
    },
    {
      "step": 1900,
      "weights": {
        "survival": 0.19686734637566192,
        "curiosity": 0.4250612289947051,
        "influence": 0.27963775144180203,
        "optimization": 0.09843367318783096
      }
    },
    {
      "step": 2000,
      "weights": {
        "survival": 0.19523094008655534,
        "curiosity": 0.4381524793075576,
        "influence": 0.2690011105626094,
        "optimization": 0.09761547004327767
      }
    },
    {
      "step": 2100,
      "weights": {
        "survival": 0.1966810783138756,
        "curiosity": 0.4265513734889954,
        "influence": 0.27842700904019113,
        "optimization": 0.0983405391569378
      }
    },
    {
      "step": 2200,
      "weights": {
        "survival": 0.1984462685879774,
        "curiosity": 0.4124298512961813,
        "influence": 0.2899007458218526,
        "optimization": 0.0992231342939887
      }
    },
    {
      "step": 2300,
      "weights": {
        "survival": 0.19838481580917855,
        "curiosity": 0.4129214735265721,
        "influence": 0.2895013027596601,
        "optimization": 0.09919240790458927
      }
    },
    {
      "step": 2400,
      "weights": {
        "survival": 0.19900184386813896,
        "curiosity": 0.4079852490548887,
        "influence": 0.29351198514290283,
        "optimization": 0.09950092193406948
      }
    },
    {
      "step": 2500,
      "weights": {
        "survival": 0.1976400497197297,
        "curiosity": 0.4188796022421628,
        "influence": 0.2846603231782426,
        "optimization": 0.09882002485986485
      }
    },
    {
      "step": 2600,
      "weights": {
        "survival": 0.19702536074622373,
        "curiosity": 0.4237971140302109,
        "influence": 0.28066484485045357,
        "optimization": 0.09851268037311187
      }
    },
    {
      "step": 2700,
      "weights": {
        "survival": 0.19878386913548235,
        "curiosity": 0.4097290469161419,
        "influence": 0.2920951493806346,
        "optimization": 0.09939193456774117
      }
    },
    {
      "step": 2800,
      "weights": {
        "survival": 0.19696432236985878,
        "curiosity": 0.4242854210411305,
        "influence": 0.2802680954040814,
        "optimization": 0.09848216118492939
      }
    },
    {
      "step": 2900,
      "weights": {
        "survival": 0.1950733893053788,
        "curiosity": 0.4394128855569704,
        "influence": 0.2679770304849614,
        "optimization": 0.0975366946526894
      }
    },
    {
      "step": 3000,
      "weights": {
        "survival": 0.19413534475763528,
        "curiosity": 0.4469172419389187,
        "influence": 0.2618797409246285,
        "optimization": 0.09706767237881764
      }
    },
    {
      "step": 3100,
      "weights": {
        "survival": 0.19544174731298383,
        "curiosity": 0.43646602149613,
        "influence": 0.2703713575343943,
        "optimization": 0.09772087365649192
      }
    },
    {
      "step": 3200,
      "weights": {
        "survival": 0.19622789500515073,
        "curiosity": 0.4301768399587947,
        "influence": 0.2754813175334792,
        "optimization": 0.09811394750257536
      }
    },
    {
      "step": 3300,
      "weights": {
        "survival": 0.19634587200572068,
        "curiosity": 0.4292330239542352,
        "influence": 0.2762481680371839,
        "optimization": 0.09817293600286034
      }
    },
    {
      "step": 3400,
      "weights": {
        "survival": 0.1947117863637197,
        "curiosity": 0.44230570909024297,
        "influence": 0.26562661136417753,
        "optimization": 0.09735589318185985
      }
    },
    {
      "step": 3500,
      "weights": {
        "survival": 0.19400037369302892,
        "curiosity": 0.447997010455769,
        "influence": 0.26100242900468756,
        "optimization": 0.09700018684651446
      }
    },
    {
      "step": 3600,
      "weights": {
        "survival": 0.1935748752563958,
        "curiosity": 0.451400997948834,
        "influence": 0.2582366891665723,
        "optimization": 0.0967874376281979
      }
    },
    {
      "step": 3700,
      "weights": {
        "survival": 0.1955024954514638,
        "curiosity": 0.4359800363882901,
        "influence": 0.27076622043451426,
        "optimization": 0.0977512477257319
      }
    },
    {
      "step": 3800,
      "weights": {
        "survival": 0.19719731742490265,
        "curiosity": 0.42242146060077934,
        "influence": 0.2817825632618667,
        "optimization": 0.09859865871245133
      }
    },
    {
      "step": 3900,
      "weights": {
        "survival": 0.19766117121422336,
        "curiosity": 0.41871063028621347,
        "influence": 0.2847976128924514,
        "optimization": 0.09883058560711168
      }
    },
    {
      "step": 4000,
      "weights": {
        "survival": 0.19958784750364506,
        "curiosity": 0.4032972199708399,
        "influence": 0.2973210087736925,
        "optimization": 0.09979392375182253
      }
    },
    {
      "step": 4100,
      "weights": {
        "survival": 0.19929807346743375,
        "curiosity": 0.40561541226053055,
        "influence": 0.2954374775383189,
        "optimization": 0.09964903673371688
      }
    },
    {
      "step": 4200,
      "weights": {
        "survival": 0.20027587434942545,
        "curiosity": 0.3977930052045968,
        "influence": 0.301793183271265,
        "optimization": 0.10013793717471273
      }
    },
    {
      "step": 4300,
      "weights": {
        "survival": 0.20083318959395408,
        "curiosity": 0.3933344832483681,
        "influence": 0.3054157323607008,
        "optimization": 0.10041659479697704
      }
    },
    {
      "step": 4400,
      "weights": {
        "survival": 0.20028441309871403,
        "curiosity": 0.3977246952102883,
        "influence": 0.3018486851416406,
        "optimization": 0.10014220654935702
      }
    },
    {
      "step": 4500,
      "weights": {
        "survival": 0.19923433254421066,
        "curiosity": 0.4061253396463154,
        "influence": 0.2950231615373686,
        "optimization": 0.09961716627210533
      }
    },
    {
      "step": 4600,
      "weights": {
        "survival": 0.19730755601946204,
        "curiosity": 0.4215395518443043,
        "influence": 0.2824991141265025,
        "optimization": 0.09865377800973102
      }
    },
    {
      "step": 4700,
      "weights": {
        "survival": 0.195854815844402,
        "curiosity": 0.4331614732447848,
        "influence": 0.2730563029886122,
        "optimization": 0.097927407922201
      }
    },
    {
      "step": 4800,
      "weights": {
        "survival": 0.19573381904052548,
        "curiosity": 0.4341294476757968,
        "influence": 0.2722698237634149,
        "optimization": 0.09786690952026274
      }
    },
    {
      "step": 4900,
      "weights": {
        "survival": 0.1956303132173797,
        "curiosity": 0.43495749426096336,
        "influence": 0.2715970359129672,
        "optimization": 0.09781515660868985
      }
    },
    {
      "step": 5000,
      "weights": {
        "survival": 0.1954023617600308,
        "curiosity": 0.43678110591975416,
        "influence": 0.2701153514401996,
        "optimization": 0.0977011808800154
      }
    },
    {
      "step": 5100,
      "weights": {
        "survival": 0.19640855387062403,
        "curiosity": 0.42873156903500864,
        "influence": 0.2766556001590554,
        "optimization": 0.09820427693531202
      }
    },
    {
      "step": 5200,
      "weights": {
        "survival": 0.19602311569032918,
        "curiosity": 0.43181507447736717,
        "influence": 0.27415025198713905,
        "optimization": 0.09801155784516459
      }
    },
    {
      "step": 5300,
      "weights": {
        "survival": 0.19667452582884584,
        "curiosity": 0.4266037933692337,
        "influence": 0.27838441788749746,
        "optimization": 0.09833726291442292
      }
    },
    {
      "step": 5400,
      "weights": {
        "survival": 0.19614689887384087,
        "curiosity": 0.4308248090092738,
        "influence": 0.274954842679965,
        "optimization": 0.09807344943692044
      }
    },
    {
      "step": 5500,
      "weights": {
        "survival": 0.19646618559135726,
        "curiosity": 0.4282705152691425,
        "influence": 0.2770302063438216,
        "optimization": 0.09823309279567863
      }
    },
    {
      "step": 5600,
      "weights": {
        "survival": 0.19550805300324867,
        "curiosity": 0.4359355759740113,
        "influence": 0.27080234452111573,
        "optimization": 0.09775402650162433
      }
    },
    {
      "step": 5700,
      "weights": {
        "survival": 0.1962606153841465,
        "curiosity": 0.42991507692682857,
        "influence": 0.27569399999695166,
        "optimization": 0.09813030769207325
      }
    },
    {
      "step": 5800,
      "weights": {
        "survival": 0.19551279842777858,
        "curiosity": 0.43589761257777204,
        "influence": 0.2708331897805601,
        "optimization": 0.09775639921388929
      }
    },
    {
      "step": 5900,
      "weights": {
        "survival": 0.19560351520179967,
        "curiosity": 0.43517187838560356,
        "influence": 0.271422848811697,
        "optimization": 0.09780175760089983
      }
    },
    {
      "step": 6000,
      "weights": {
        "survival": 0.19598387415802634,
        "curiosity": 0.43212900673579013,
        "influence": 0.2738951820271704,
        "optimization": 0.09799193707901317
      }
    },
    {
      "step": 6100,
      "weights": {
        "survival": 0.19690932119779317,
        "curiosity": 0.42472543041765554,
        "influence": 0.2799105877856547,
        "optimization": 0.09845466059889658
      }
    },
    {
      "step": 6200,
      "weights": {
        "survival": 0.19528598701978106,
        "curiosity": 0.43771210384175263,
        "influence": 0.2693589156285759,
        "optimization": 0.09764299350989053
      }
    },
    {
      "step": 6300,
      "weights": {
        "survival": 0.19574018208207794,
        "curiosity": 0.4340785433433774,
        "influence": 0.2723111835335057,
        "optimization": 0.09787009104103897
      }
    },
    {
      "step": 6400,
      "weights": {
        "survival": 0.19408130812783753,
        "curiosity": 0.44734953497730057,
        "influence": 0.2615285028309431,
        "optimization": 0.09704065406391876
      }
    },
    {
      "step": 6500,
      "weights": {
        "survival": 0.193547235985203,
        "curiosity": 0.4516221121183771,
        "influence": 0.25805703390381846,
        "optimization": 0.0967736179926015
      }
    },
    {
      "step": 6600,
      "weights": {
        "survival": 0.1926815649956403,
        "curiosity": 0.4585474800348787,
        "influence": 0.25243017247166094,
        "optimization": 0.09634078249782015
      }
    },
    {
      "step": 6700,
      "weights": {
        "survival": 0.19443703127752418,
        "curiosity": 0.44450374977980744,
        "influence": 0.26384070330390624,
        "optimization": 0.09721851563876209
      }
    },
    {
      "step": 6800,
      "weights": {
        "survival": 0.19410522782958314,
        "curiosity": 0.44715817736333596,
        "influence": 0.2616839808922894,
        "optimization": 0.09705261391479157
      }
    },
    {
      "step": 6900,
      "weights": {
        "survival": 0.19355507329543933,
        "curiosity": 0.45155941363648616,
        "influence": 0.25810797642035477,
        "optimization": 0.09677753664771967
      }
    },
    {
      "step": 7000,
      "weights": {
        "survival": 0.19400912499847475,
        "curiosity": 0.4479270000122029,
        "influence": 0.26105931249008496,
        "optimization": 0.09700456249923738
      }
    },
    {
      "step": 7100,
      "weights": {
        "survival": 0.19593841393041636,
        "curiosity": 0.4324926885566701,
        "influence": 0.2735996905477054,
        "optimization": 0.09796920696520818
      }
    },
    {
      "step": 7200,
      "weights": {
        "survival": 0.1948789064413217,
        "curiosity": 0.4409687484694274,
        "influence": 0.2667128918685901,
        "optimization": 0.09743945322066085
      }
    },
    {
      "step": 7300,
      "weights": {
        "survival": 0.19573079202127946,
        "curiosity": 0.434153663829765,
        "influence": 0.2722501481383158,
        "optimization": 0.09786539601063973
      }
    },
    {
      "step": 7400,
      "weights": {
        "survival": 0.19582871695351897,
        "curiosity": 0.4333702643718488,
        "influence": 0.2728866601978727,
        "optimization": 0.09791435847675949
      }
    },
    {
      "step": 7500,
      "weights": {
        "survival": 0.19441886495576766,
        "curiosity": 0.44464908035385964,
        "influence": 0.26372262221248893,
        "optimization": 0.09720943247788383
      }
    },
    {
      "step": 7600,
      "weights": {
        "survival": 0.19417582523563637,
        "curiosity": 0.44659339811490983,
        "influence": 0.2621428640316356,
        "optimization": 0.09708791261781818
      }
    },
    {
      "step": 7700,
      "weights": {
        "survival": 0.19333203099546528,
        "curiosity": 0.45334375203627825,
        "influence": 0.2566582014705237,
        "optimization": 0.09666601549773264
      }
    },
    {
      "step": 7800,
      "weights": {
        "survival": 0.19246915723013863,
        "curiosity": 0.46024674215889183,
        "influence": 0.25104952199590025,
        "optimization": 0.09623457861506932
      }
    },
    {
      "step": 7900,
      "weights": {
        "survival": 0.19361889125631296,
        "curiosity": 0.45104886994949717,
        "influence": 0.25852279316603344,
        "optimization": 0.09680944562815648
      }
    },
    {
      "step": 8000,
      "weights": {
        "survival": 0.19191010059861627,
        "curiosity": 0.46471919521107063,
        "influence": 0.24741565389100498,
        "optimization": 0.09595505029930813
      }
    },
    {
      "step": 8100,
      "weights": {
        "survival": 0.1911249198236889,
        "curiosity": 0.4710006414104896,
        "influence": 0.2423119788539771,
        "optimization": 0.09556245991184445
      }
    },
    {
      "step": 8200,
      "weights": {
        "survival": 0.19053838756256283,
        "curiosity": 0.4756928994994983,
        "influence": 0.23849951915665754,
        "optimization": 0.09526919378128142
      }
    },
    {
      "step": 8300,
      "weights": {
        "survival": 0.18885220238585954,
        "curiosity": 0.48918238091312444,
        "influence": 0.22753931550808626,
        "optimization": 0.09442610119292977
      }
    },
    {
      "step": 8400,
      "weights": {
        "survival": 0.190209846089536,
        "curiosity": 0.4783212312837127,
        "influence": 0.2363639995819833,
        "optimization": 0.095104923044768
      }
    },
    {
      "step": 8500,
      "weights": {
        "survival": 0.19085863440088968,
        "curiosity": 0.47313092479288327,
        "influence": 0.24058112360578218,
        "optimization": 0.09542931720044484
      }
    },
    {
      "step": 8600,
      "weights": {
        "survival": 0.19065753981651734,
        "curiosity": 0.4747396814678618,
        "influence": 0.2392740088073621,
        "optimization": 0.09532876990825867
      }
    },
    {
      "step": 8700,
      "weights": {
        "survival": 0.18929540142044884,
        "curiosity": 0.48563678863640974,
        "influence": 0.23042010923291692,
        "optimization": 0.09464770071022442
      }
    },
    {
      "step": 8800,
      "weights": {
        "survival": 0.18931767523895668,
        "curiosity": 0.4854585980883472,
        "influence": 0.2305648890532178,
        "optimization": 0.09465883761947834
      }
    },
    {
      "step": 8900,
      "weights": {
        "survival": 0.18746250332229517,
        "curiosity": 0.5002999734216392,
        "influence": 0.21850627159491798,
        "optimization": 0.09373125166114758
      }
    },
    {
      "step": 9000,
      "weights": {
        "survival": 0.1858462526776903,
        "curiosity": 0.513229978578478,
        "influence": 0.20800064240498653,
        "optimization": 0.09292312633884516
      }
    },
    {
      "step": 9100,
      "weights": {
        "survival": 0.1864706618293524,
        "curiosity": 0.5082347053651812,
        "influence": 0.21205930189079011,
        "optimization": 0.0932353309146762
      }
    },
    {
      "step": 9200,
      "weights": {
        "survival": 0.18801941942158362,
        "curiosity": 0.49584464462733163,
        "influence": 0.22212622624029296,
        "optimization": 0.09400970971079181
      }
    },
    {
      "step": 9300,
      "weights": {
        "survival": 0.18828400271299578,
        "curiosity": 0.4937279782960343,
        "influence": 0.22384601763447204,
        "optimization": 0.09414200135649789
      }
    },
    {
      "step": 9400,
      "weights": {
        "survival": 0.18751908959231614,
        "curiosity": 0.4998472832614715,
        "influence": 0.2188740823500544,
        "optimization": 0.09375954479615807
      }
    },
    {
      "step": 9500,
      "weights": {
        "survival": 0.18575742619666072,
        "curiosity": 0.5139405904267146,
        "influence": 0.20742327027829432,
        "optimization": 0.09287871309833036
      }
    },
    {
      "step": 9600,
      "weights": {
        "survival": 0.18509214261636045,
        "curiosity": 0.5192628590691168,
        "influence": 0.20309892700634247,
        "optimization": 0.09254607130818022
      }
    },
    {
      "step": 9700,
      "weights": {
        "survival": 0.18504004949594985,
        "curiosity": 0.5196796040324017,
        "influence": 0.20276032172367356,
        "optimization": 0.09252002474797492
      }
    },
    {
      "step": 9800,
      "weights": {
        "survival": 0.1834297485864892,
        "curiosity": 0.532562011308087,
        "influence": 0.19229336581217923,
        "optimization": 0.0917148742932446
      }
    },
    {
      "step": 9900,
      "weights": {
        "survival": 0.18487572114671277,
        "curiosity": 0.5209942308262981,
        "influence": 0.20169218745363263,
        "optimization": 0.09243786057335639
      }
    }
  ]
}